<annotation>
	<folder>sahil_slot</folder>
	<filename>77.jpg</filename>
	<path>/home/hrushikesh/Downloads/sahil_slot/77.jpg</path>
	<source>
		<database>Unknown</database>
	</source>
	<size>
		<width>640</width>
		<height>640</height>
		<depth>3</depth>
	</size>
	<segmented>0</segmented>
	<object>
		<name>invoice_title</name>
		<pose>Unspecified</pose>
		<truncated>0</truncated>
		<difficult>0</difficult>
		<bndbox>
			<xmin>142</xmin>
			<ymin>62</ymin>
			<xmax>454</xmax>
			<ymax>195</ymax>
		</bndbox>
	</object>
	<object>
		<name>invoice_total</name>
		<pose>Unspecified</pose>
		<truncated>0</truncated>
		<difficult>0</difficult>
		<bndbox>
			<xmin>99</xmin>
			<ymin>554</ymin>
			<xmax>593</xmax>
			<ymax>611</ymax>
		</bndbox>
	</object>
	<object>
		<name>invoice_table</name>
		<pose>Unspecified</pose>
		<truncated>0</truncated>
		<difficult>0</difficult>
		<bndbox>
			<xmin>45</xmin>
			<ymin>304</ymin>
			<xmax>570</xmax>
			<ymax>400</ymax>
		</bndbox>
	</object>
</annotation>
